trytond/modules/health_reporting/COPYING
trytond/modules/health_reporting/README.rst
trytond/modules/health_reporting/__init__.py
trytond/modules/health_reporting/data/messages/messages.xml
trytond/modules/health_reporting/health_reporting_report.xml
trytond/modules/health_reporting/health_reporting_view.xml
trytond/modules/health_reporting/locale/ar.po
trytond/modules/health_reporting/locale/de.po
trytond/modules/health_reporting/locale/el.po
trytond/modules/health_reporting/locale/eo.po
trytond/modules/health_reporting/locale/es.po
trytond/modules/health_reporting/locale/fr.po
trytond/modules/health_reporting/locale/health_reporting.pot
trytond/modules/health_reporting/locale/it_IT.po
trytond/modules/health_reporting/locale/ja_JP.po
trytond/modules/health_reporting/locale/ka.po
trytond/modules/health_reporting/locale/lo.po
trytond/modules/health_reporting/locale/pt_BR.po
trytond/modules/health_reporting/locale/sv.po
trytond/modules/health_reporting/locale/tr.po
trytond/modules/health_reporting/locale/uk.po
trytond/modules/health_reporting/locale/zh_CN.po
trytond/modules/health_reporting/pyproject.toml
trytond/modules/health_reporting/report/__init__.py
trytond/modules/health_reporting/report/epidemics_report.odt
trytond/modules/health_reporting/report/epidemics_report.py
trytond/modules/health_reporting/report/summary_report.odt
trytond/modules/health_reporting/report/summary_report.py
trytond/modules/health_reporting/tests/__init__.py
trytond/modules/health_reporting/tests/test_health_reporting.py
trytond/modules/health_reporting/tryton.cfg
trytond/modules/health_reporting/view/epidemics_report_open_start_form.xml
trytond/modules/health_reporting/view/evaluations_doctor_graph.xml
trytond/modules/health_reporting/view/evaluations_doctor_tree.xml
trytond/modules/health_reporting/view/evaluations_open_start_form.xml
trytond/modules/health_reporting/view/evaluations_sector_graph.xml
trytond/modules/health_reporting/view/evaluations_sector_tree.xml
gnuhealth_reporting-5.0.2.dist-info/METADATA
gnuhealth_reporting-5.0.2.dist-info/WHEEL
gnuhealth_reporting-5.0.2.dist-info/licenses/COPYING
gnuhealth_reporting-5.0.2.dist-info/RECORD
